<?xml version="1.0"?>
<entity-def>
    <!--
        **** Example code to write entity defintion ****
            <table name="TestEntityReader">
                <column name="Id" data-type="int" primary-key="true" distinct="true" null="false" auto-increment="true"/>
                <column name="TestColumn1" data-type="varchar" column-size="1" null="false"/>
                <column name="TestColumn2" data-type="int" null="false"/>
                <column name="TestColumn3" data-type="varchar" column-size="3"/>
                <column name="TestColumn4" data-type="varchar" column-size="4"/>
                <column name="TestColumn5" data-type="varchar" column-size="5" null="false"/>
                <column name="TestColumn6" data-type="varchar" column-size="7"/>
            </table>
    -->
    <table name="TestEntityReader">
        <column name="Id" data-type="int" primary-key="true" distinct="true" null="false" auto-increment="true"/>
        <column name="TestColumn1" data-type="varchar" column-size="1" null="false"/>
        <column name="TestColumn2" data-type="int" null="false"/>
        <column name="TestColumn3" data-type="varchar" column-size="3"/>
        <column name="TestColumn4" data-type="varchar" column-size="4"/>
        <column name="TestColumn5" data-type="varchar" column-size="5" null="false"/>
        <column name="TestColumn7" data-type="int" column-size="8" null="false"/>
    </table>
</entity-def>